{
  "seller": [
    {
      "name": "srinath",
      "email": "abc@gmail.com",
      "password": "abc@1230",
      "id": 1
    }
  ],
  "products": [
    {
      "name": "Iphon14pro",
      "price": "1,49,998",
      "category": "smartPhone",
      "Description": "hello users this is my brand new Iphone",
      "image": "https://m.media-amazon.com/images/I/61XO4bORHUL._SL1500_.jpg",
      "id": 3
    },
    {
      "name": "macbookpro",
      "price": "1,99,999",
      "category": "laptop",
      "Description": "apple laptop",
      "image": "https://m.media-amazon.com/images/I/61Ph34V0YAL._SL1500_.jpg",
      "id": 5
    },
    {
      "name": "macbookpro15",
      "price": "1,98,998",
      "category": "laptop",
      "Description": "apple ilaptop",
      "image": "https://m.media-amazon.com/images/I/61ZQEkRzQaL._SL1080_.jpg",
      "id": 5
    },
    {
      "name": "Iphon14pro",
      "price": "1,49,998",
      "category": "smartPhone",
      "Description": "hello users this is my brand new Iphone",
      "image": "https://m.media-amazon.com/images/I/61XO4bORHUL._SL1500_.jpg",
      "id": 3
    },
    {
      "name": "macbookpro",
      "price": "1,99,999",
      "category": "laptop",
      "Description": "apple laptop",
      "image": "https://m.media-amazon.com/images/I/61Ph34V0YAL._SL1500_.jpg",
      "id": 5
    },
    {
      "name": "macbookpro15",
      "price": "1,98,998",
      "category": "laptop",
      "Description": "apple ilaptop",
      "image": "https://m.media-amazon.com/images/I/61ZQEkRzQaL._SL1080_.jpg",
      "id": 5
    },
    {
      "name": "Iphon14pro",
      "price": "1,49,998",
      "category": "smartPhone",
      "Description": "hello users this is my brand new Iphone",
      "image": "https://m.media-amazon.com/images/I/61XO4bORHUL._SL1500_.jpg",
      "id": 3
    },
    {
      "name": "macbookpro",
      "price": "1,99,999",
      "category": "laptop",
      "Description": "apple laptop",
      "image": "https://m.media-amazon.com/images/I/61Ph34V0YAL._SL1500_.jpg",
      "id": 5
    },
    {
      "name": "macbookpro15",
      "price": "1,98,998",
      "category": "laptop",
      "Description": "apple ilaptop",
      "image": "https://m.media-amazon.com/images/I/61ZQEkRzQaL._SL1080_.jpg",
      "id": 5
    },
    {
      "name": "Iphon14pro",
      "price": "1,49,998",
      "category": "smartPhone",
      "Description": "hello users this is my brand new Iphone",
      "image": "https://m.media-amazon.com/images/I/61XO4bORHUL._SL1500_.jpg",
      "id": 3
    },
    {
      "name": "macbookpro",
      "price": "1,99,999",
      "category": "laptop",
      "Description": "apple laptop",
      "image": "https://m.media-amazon.com/images/I/61Ph34V0YAL._SL1500_.jpg",
      "id": 5
    },
    {
      "name": "macbookpro15",
      "price": "1,98,998",
      "category": "laptop",
      "Description": "apple ilaptop",
      "image": "https://m.media-amazon.com/images/I/61ZQEkRzQaL._SL1080_.jpg",
      "id": 5
    }
  ]
}